dict_patterns/__init__.py
dict_patterns/dict_matcher.py
dict_patterns/exceptions.py
dict_patterns/patterns.py
dict_patterns/py.typed
dict_patterns/pytest_plugin.py
dict_patterns-0.3.0.dist-info/WHEEL
dict_patterns-0.3.0.dist-info/entry_points.txt
dict_patterns-0.3.0.dist-info/METADATA
dict_patterns-0.3.0.dist-info/RECORD
