Metadata-Version: 2.3
Name: dict-patterns
Version: 0.3.0
Summary: A template engine for dictionary data – useful for tests!
Keywords: dictionary,pattern-matching,template-engine,testing,validation,json,regex,pytest,data-validation
Author: Antonio Feregrino
Author-email: Antonio Feregrino <antonio.feregrino@gmail.com>
License: MIT
Classifier: Development Status :: 4 - Beta
Classifier: Intended Audience :: Developers
Classifier: License :: OSI Approved :: MIT License
Classifier: Operating System :: OS Independent
Classifier: Programming Language :: Python :: 3
Classifier: Programming Language :: Python :: 3.10
Classifier: Programming Language :: Python :: 3.11
Classifier: Programming Language :: Python :: 3.12
Classifier: Programming Language :: Python :: 3.13
Classifier: Topic :: Software Development :: Testing
Classifier: Topic :: Software Development :: Libraries :: Python Modules
Classifier: Topic :: Text Processing :: Markup
Classifier: Topic :: Utilities
Classifier: Typing :: Typed
Requires-Dist: pytest>=8.4.1 ; extra == 'pytest'
Maintainer: Antonio Feregrino
Maintainer-email: Antonio Feregrino <antonio.feregrino@gmail.com>
Requires-Python: >=3.10
Project-URL: Homepage, https://github.com/fferegrino/dict-patterns
Project-URL: Issues, https://github.com/fferegrino/dict-patterns/issues
Project-URL: Repository, https://github.com/fferegrino/dict-patterns.git
Provides-Extra: pytest
